berycker/__init__.py
berycker/build.py
berycker/cli.py
berycker/initialize.py
berycker/statements.py
berycker/tools.py
berycker-0.2.0.dist-info/entry_points.txt
berycker-0.2.0.dist-info/WHEEL
berycker-0.2.0.dist-info/METADATA
berycker-0.2.0.dist-info/RECORD
