Metadata-Version: 2.1
Name: berycker
Version: 0.2.0
Summary: Docker-like tool to set up a headless RaspberryPi or linux
Home-page: https://probio.basashi.tech/introduction/
License: MIT
Author: Tomoki Murayama
Author-email: muratomo.0205@gmail.com
Requires-Python: >=3.8,<4.0
Classifier: License :: OSI Approved :: MIT License
Classifier: Programming Language :: Python :: 3
Classifier: Programming Language :: Python :: 3.8
Requires-Dist: fire (>=0.3.1,<0.4.0)
Requires-Dist: paramiko (>=2.7.2,<3.0.0)
Requires-Dist: psutil (>=5.7.2,<6.0.0)
Requires-Dist: termcolor (>=1.1.0,<2.0.0)
Project-URL: Repository, https://github.com/basashi-G/berycker
